satellite_image_classification/__init__.py
satellite_image_classification/classification.py
satellite_image_classification-0.1.0.dist-info/METADATA
satellite_image_classification-0.1.0.dist-info/WHEEL
satellite_image_classification-0.1.0.dist-info/entry_points.txt
satellite_image_classification-0.1.0.dist-info/top_level.txt
satellite_image_classification-0.1.0.dist-info/RECORD
