Metadata-Version: 2.1
Name: satellite_image_classification
Version: 0.1.0
Requires-Dist: rasterio
Requires-Dist: numpy
Requires-Dist: scikit-learn
